pmtiles_mosaic/__init__.py
pmtiles_mosaic/_version.py
pmtiles_mosaic/disk_source.py
pmtiles_mosaic/download_mosaic.py
pmtiles_mosaic/logger.py
pmtiles_mosaic/mbtiles_source.py
pmtiles_mosaic/partition.py
pmtiles_mosaic/partition_basic.py
pmtiles_mosaic/pmtiles_source.py
pmtiles_mosaic/stacked_source.py
pmtiles_mosaic/tile_sources.py
pmtiles_mosaic/tiles_common.py
pmtiles_mosaic-0.1.6.dist-info/METADATA
pmtiles_mosaic-0.1.6.dist-info/WHEEL
pmtiles_mosaic-0.1.6.dist-info/entry_points.txt
pmtiles_mosaic-0.1.6.dist-info/licenses/LICENSE
pmtiles_mosaic-0.1.6.dist-info/RECORD
