Metadata-Version: 2.4
Name: pmtiles_mosaic
Version: 0.1.6
Summary: Tools to partition and rejoin PMTiles files as mosaics
Project-URL: homepage, https://github.com/ramSeraph/pmtiles_mosaic
Project-URL: repository, https://github.com/ramSeraph/pmtiles_mosaic.git
Author-email: Sreeram Kandimalla <kandimalla.sreeram@gmail.com>
License-File: LICENSE
Requires-Python: >=3.12
Requires-Dist: aiohttp>=3.12.15
Requires-Dist: colorlog>=6.9.0
Requires-Dist: mercantile>=1.2.1
Requires-Dist: pillow>=11.3.0
Requires-Dist: pmtiles==3.4.1
Requires-Dist: pypdl>=1.5.6
